{"success": true, "results": [{"date": "2021-03-15", "name": "Ae", "id": "USA_US-None", "total_count": 1, "lineage_count": 0, "cum_total_count": 1, "cum_lineage_count": 0, "proportion": 0.0, "proportion_ci_lower": 0.00038558098075590136, "proportion_ci_upper": 0.8532536836904249}, {"date": "2021-04-12", "name": "Alabama", "id": "USA_US-AL", "total_count": 4, "lineage_count": 0, "cum_total_count": 254, "cum_lineage_count": 7, "proportion": 0.027559055118110236, "proportion_ci_lower": 0.012409796239751565, "proportion_ci_upper": 0.05334219869879209}, {"date": "2021-04-15", "name": "Alaska", "id": "USA_US-AK", "total_count": 4, "lineage_count": 0, "cum_total_count": 449, "cum_lineage_count": 0, "proportion": 0.0, "proportion_ci_lower": 1.093008823995058e-06, "proportion_ci_upper": 0.0055758096202449614}, {"date": "2021-04-15", "name": "Arizona", "id": "USA_US-AZ", "total_count": 2, "lineage_count": 0, "cum_total_count": 2023, "cum_lineage_count": 37, "proportion": 0.01828966880869995, "proportion_ci_lower": 0.01311765349679746, "proportion_ci_upper": 0.02483729931143286}, {"date": "2021-04-09", "name": "Arkansas", "id": "USA_US-AR", "total_count": 3, "lineage_count": 0, "cum_total_count": 121, "cum_lineage_count": 2, "proportion": 0.01652892561983471, "proportion_ci_lower": 0.0034502739182727623, "proportion_ci_upper": 0.05196123260410623}, {"date": "2021-04-15", "name": "California", "id": "USA_US-CA", "total_count": 55, "lineage_count": 2, "cum_total_count": 11052, "cum_lineage_count": 220, "proportion": 0.019905899384726745, "proportion_ci_lower": 0.017425992578997008, "proportion_ci_upper": 0.022637173659232346}, {"date": "2021-04-13", "name": "Colorado", "id": "USA_US-CO", "total_count": 5, "lineage_count": 2, "cum_total_count": 3999, "cum_lineage_count": 55, "proportion": 0.013753438359589898, "proportion_ci_lower": 0.010486109216838246, "proportion_ci_upper": 0.017723756428382642}, {"date": "2021-04-17", "name": "Connecticut", "id": "USA_US-CT", "total_count": 8, "lineage_count": 0, "cum_total_count": 2394, "cum_lineage_count": 419, "proportion": 0.17502088554720133, "proportion_ci_lower": 0.16019684245414545, "proportion_ci_upper": 0.19063014187426708}, {"date": "2021-04-08", "name": "Delaware", "id": "USA_US-DE", "total_count": 1, "lineage_count": 1, "cum_total_count": 303, "cum_lineage_count": 86, "proportion": 0.2838283828382838, "proportion_ci_lower": 0.2352942233933688, "proportion_ci_upper": 0.33646981666440856}, {"date": "2021-04-13", "name": "District of Columbia", "id": "USA_US-DC", "total_count": 3, "lineage_count": 0, "cum_total_count": 176, "cum_lineage_count": 13, "proportion": 0.07386363636363637, "proportion_ci_lower": 0.04203394398435069, "proportion_ci_upper": 0.11954185178742505}, {"date": "2021-04-19", "name": "Florida", "id": "USA_US-FL", "total_count": 1, "lineage_count": 0, "cum_total_count": 10268, "cum_lineage_count": 570, "proportion": 0.055512271133619014, "proportion_ci_lower": 0.05120808059163702, "proportion_ci_upper": 0.06006698605324989}, {"date": "2021-03-10", "name": "GA", "id": "USA_US-None", "total_count": 1, "lineage_count": 1, "cum_total_count": 1, "cum_lineage_count": 1, "proportion": 1.0, "proportion_ci_lower": 0.14674631630957516, "proportion_ci_upper": 0.9996144190192441}, {"date": "2021-04-13", "name": "Georgia", "id": "USA_US-GA", "total_count": 2, "lineage_count": 0, "cum_total_count": 1775, "cum_lineage_count": 42, "proportion": 0.023661971830985916, "proportion_ci_lower": 0.01734568728842524, "proportion_ci_upper": 0.031528660147507326}, {"date": "2021-04-12", "name": "Hawaii", "id": "USA_US-HI", "total_count": 1, "lineage_count": 1, "cum_total_count": 257, "cum_lineage_count": 4, "proportion": 0.01556420233463035, "proportion_ci_lower": 0.005275810275363786, "proportion_ci_upper": 0.03657849635362698}, {"date": "2021-04-09", "name": "Idaho", "id": "USA_US-ID", "total_count": 2, "lineage_count": 0, "cum_total_count": 355, "cum_lineage_count": 4, "proportion": 0.011267605633802818, "proportion_ci_lower": 0.0038149425062836795, "proportion_ci_upper": 0.026566565226480154}, {"date": "2021-04-15", "name": "Illinois", "id": "USA_US-IL", "total_count": 1, "lineage_count": 0, "cum_total_count": 4114, "cum_lineage_count": 89, "proportion": 0.02163344676713661, "proportion_ci_lower": 0.01751782205790877, "proportion_ci_upper": 0.026421561401429372}, {"date": "2021-04-12", "name": "Indiana", "id": "USA_US-IN", "total_count": 11, "lineage_count": 0, "cum_total_count": 1719, "cum_lineage_count": 37, "proportion": 0.02152414194299011, "proportion_ci_lower": 0.015444318025931198, "proportion_ci_upper": 0.029211776691653646}, {"date": "2021-04-12", "name": "Iowa", "id": "USA_US-IA", "total_count": 1, "lineage_count": 0, "cum_total_count": 247, "cum_lineage_count": 1, "proportion": 0.004048582995951417, "proportion_ci_lower": 0.00043717994128552104, "proportion_ci_upper": 0.01876482039089089}, {"date": "2021-04-22", "name": "Kansas", "id": "USA_US-KS", "total_count": 3, "lineage_count": 0, "cum_total_count": 543, "cum_lineage_count": 13, "proportion": 0.02394106813996317, "proportion_ci_lower": 0.013484372708904865, "proportion_ci_upper": 0.039440845282748715}, {"date": "2021-04-09", "name": "Kentucky", "id": "USA_US-KY", "total_count": 3, "lineage_count": 0, "cum_total_count": 568, "cum_lineage_count": 10, "proportion": 0.017605633802816902, "proportion_ci_lower": 0.00908683511028172, "proportion_ci_upper": 0.03100510419993452}, {"date": "2021-04-15", "name": "Las Vegas", "id": "USA_US-None", "total_count": 1, "lineage_count": 0, "cum_total_count": 19, "cum_lineage_count": 0, "proportion": 0.0, "proportion_ci_lower": 2.5505812625695268e-05, "proportion_ci_upper": 0.12230940431991393}, {"date": "2021-04-13", "name": "Louisiana", "id": "USA_US-LA", "total_count": 1, "lineage_count": 0, "cum_total_count": 328, "cum_lineage_count": 9, "proportion": 0.027439024390243903, "proportion_ci_lower": 0.013661752386672601, "proportion_ci_upper": 0.049475937040445506}, {"date": "2021-04-14", "name": "Maine", "id": "USA_US-ME", "total_count": 5, "lineage_count": 0, "cum_total_count": 655, "cum_lineage_count": 38, "proportion": 0.05801526717557252, "proportion_ci_lower": 0.04202834925739883, "proportion_ci_upper": 0.07789464561805182}, {"date": "2021-04-19", "name": "Maryland", "id": "USA_US-MD", "total_count": 2, "lineage_count": 0, "cum_total_count": 3466, "cum_lineage_count": 243, "proportion": 0.07010963646855164, "proportion_ci_lower": 0.061966468374095716, "proportion_ci_upper": 0.07897032497241141}, {"date": "2021-04-15", "name": "Massachusetts", "id": "USA_US-MA", "total_count": 18, "lineage_count": 1, "cum_total_count": 4737, "cum_lineage_count": 329, "proportion": 0.06945324044754064, "proportion_ci_lower": 0.062475636133621774, "proportion_ci_upper": 0.07695673332099473}, {"date": "2021-04-14", "name": "Michigan", "id": "USA_US-MI", "total_count": 2, "lineage_count": 0, "cum_total_count": 7144, "cum_lineage_count": 144, "proportion": 0.020156774916013438, "proportion_ci_lower": 0.01708931012398855, "proportion_ci_upper": 0.023612837928178032}, {"date": "2021-04-20", "name": "Minnesota", "id": "USA_US-MN", "total_count": 2, "lineage_count": 0, "cum_total_count": 6595, "cum_lineage_count": 90, "proportion": 0.013646702047005308, "proportion_ci_lower": 0.01105557269154606, "proportion_ci_upper": 0.0166643986651972}, {"date": "2021-04-13", "name": "Mississippi", "id": "USA_US-MS", "total_count": 3, "lineage_count": 0, "cum_total_count": 268, "cum_lineage_count": 3, "proportion": 0.011194029850746268, "proportion_ci_lower": 0.003162528289200611, "proportion_ci_upper": 0.029569122979987483}, {"date": "2021-04-12", "name": "Missouri", "id": "USA_US-MO", "total_count": 2, "lineage_count": 0, "cum_total_count": 498, "cum_lineage_count": 16, "proportion": 0.0321285140562249, "proportion_ci_lower": 0.019239383136356553, "proportion_ci_upper": 0.05042413370231991}, {"date": "2021-04-26", "name": "Montana", "id": "USA_US-MT", "total_count": 1, "lineage_count": 0, "cum_total_count": 236, "cum_lineage_count": 5, "proportion": 0.0211864406779661, "proportion_ci_lower": 0.008129043027300992, "proportion_ci_upper": 0.04580823431894265}, {"date": "2021-04-20", "name": "Nebraska", "id": "USA_US-NE", "total_count": 2, "lineage_count": 0, "cum_total_count": 345, "cum_lineage_count": 2, "proportion": 0.005797101449275362, "proportion_ci_lower": 0.001206553053883293, "proportion_ci_upper": 0.01846582291863408}, {"date": "2021-04-19", "name": "Nevada", "id": "USA_US-NV", "total_count": 5, "lineage_count": 0, "cum_total_count": 527, "cum_lineage_count": 4, "proportion": 0.007590132827324478, "proportion_ci_lower": 0.002567283624585571, "proportion_ci_upper": 0.01794546977048017}, {"date": "2021-04-13", "name": "New Hampshire", "id": "USA_US-NH", "total_count": 1, "lineage_count": 0, "cum_total_count": 607, "cum_lineage_count": 29, "proportion": 0.047775947281713346, "proportion_ci_lower": 0.03290785649943204, "proportion_ci_upper": 0.06693920698825429}, {"date": "2021-04-17", "name": "New Jersey", "id": "USA_US-NJ", "total_count": 11, "lineage_count": 7, "cum_total_count": 5621, "cum_lineage_count": 1363, "proportion": 0.24248354385340687, "proportion_ci_lower": 0.23141390833806005, "proportion_ci_upper": 0.2538182952336123}, {"date": "2021-04-12", "name": "New Mexico", "id": "USA_US-NM", "total_count": 1, "lineage_count": 0, "cum_total_count": 557, "cum_lineage_count": 2, "proportion": 0.003590664272890485, "proportion_ci_lower": 0.0007468780450942756, "proportion_ci_upper": 0.011468584957237349}, {"date": "2021-04-22", "name": "New York", "id": "USA_US-NY", "total_count": 53, "lineage_count": 12, "cum_total_count": 14698, "cum_lineage_count": 4005, "proportion": 0.2724860525241529, "proportion_ci_lower": 0.2653333600244459, "proportion_ci_upper": 0.2797283382143745}, {"date": "2021-04-15", "name": "North Carolina", "id": "USA_US-NC", "total_count": 2, "lineage_count": 2, "cum_total_count": 2117, "cum_lineage_count": 315, "proportion": 0.1487954652810581, "proportion_ci_lower": 0.13411934321556465, "proportion_ci_upper": 0.1644310864756332}, {"date": "2021-04-11", "name": "North Dakota", "id": "USA_US-ND", "total_count": 3, "lineage_count": 0, "cum_total_count": 267, "cum_lineage_count": 5, "proportion": 0.018726591760299626, "proportion_ci_lower": 0.00718058105700659, "proportion_ci_upper": 0.040554313851371315}, {"date": "2021-03-18", "name": "North Dalota", "id": "USA_US-None", "total_count": 1, "lineage_count": 0, "cum_total_count": 1, "cum_lineage_count": 0, "proportion": 0.0, "proportion_ci_lower": 0.00038558098075590136, "proportion_ci_upper": 0.8532536836904249}, {"date": "2021-04-15", "name": "Ohio", "id": "USA_US-OH", "total_count": 193, "lineage_count": 0, "cum_total_count": 2682, "cum_lineage_count": 34, "proportion": 0.01267710663683818, "proportion_ci_lower": 0.00895036662552701, "proportion_ci_upper": 0.017453617307860325}, {"date": "2021-04-13", "name": "Oklahoma", "id": "USA_US-OK", "total_count": 1, "lineage_count": 0, "cum_total_count": 122, "cum_lineage_count": 2, "proportion": 0.01639344262295082, "proportion_ci_lower": 0.00342186584313027, "proportion_ci_upper": 0.051543891109500306}, {"date": "2021-04-19", "name": "Oregon", "id": "USA_US-OR", "total_count": 2, "lineage_count": 0, "cum_total_count": 690, "cum_lineage_count": 34, "proportion": 0.04927536231884058, "proportion_ci_lower": 0.034972011024121244, "proportion_ci_upper": 0.06734668437295876}, {"date": "2021-04-16", "name": "Pennsylvania", "id": "USA_US-PA", "total_count": 1, "lineage_count": 0, "cum_total_count": 5262, "cum_lineage_count": 578, "proportion": 0.10984416571645762, "proportion_ci_lower": 0.1016102259872849, "proportion_ci_upper": 0.11850715171210391}, {"date": "2021-04-12", "name": "Puerto Rico", "id": "USA_US-None", "total_count": 2, "lineage_count": 0, "cum_total_count": 304, "cum_lineage_count": 21, "proportion": 0.06907894736842106, "proportion_ci_lower": 0.04458390896812927, "proportion_ci_upper": 0.1017213745026323}, {"date": "2021-04-15", "name": "Rhode Island", "id": "USA_US-RI", "total_count": 1, "lineage_count": 0, "cum_total_count": 1022, "cum_lineage_count": 59, "proportion": 0.057729941291585124, "proportion_ci_lower": 0.044664742507321845, "proportion_ci_upper": 0.07329454898664245}, {"date": "2021-04-10", "name": "South Carolina", "id": "USA_US-SC", "total_count": 1, "lineage_count": 0, "cum_total_count": 339, "cum_lineage_count": 15, "proportion": 0.04424778761061947, "proportion_ci_lower": 0.026090928615568335, "proportion_ci_upper": 0.07012893348922278}, {"date": "2021-04-06", "name": "South Dakota", "id": "USA_US-SD", "total_count": 3, "lineage_count": 1, "cum_total_count": 155, "cum_lineage_count": 4, "proportion": 0.025806451612903226, "proportion_ci_lower": 0.00877207980662707, "proportion_ci_upper": 0.06018316704242832}, {"date": "2021-04-12", "name": "Tennessee", "id": "USA_US-TN", "total_count": 9, "lineage_count": 0, "cum_total_count": 1272, "cum_lineage_count": 19, "proportion": 0.014937106918238994, "proportion_ci_lower": 0.009322613470441738, "proportion_ci_upper": 0.02275104118778637}, {"date": "2021-04-17", "name": "Texas", "id": "USA_US-TX", "total_count": 6, "lineage_count": 0, "cum_total_count": 5194, "cum_lineage_count": 48, "proportion": 0.009241432422025414, "proportion_ci_lower": 0.00690434339460464, "proportion_ci_upper": 0.012124772449529808}, {"date": "2021-04-10", "name": "Unknown", "id": "USA_US-None", "total_count": 12, "lineage_count": 0, "cum_total_count": 41, "cum_lineage_count": 2, "proportion": 0.04878048780487805, "proportion_ci_lower": 0.010274028167840683, "proportion_ci_upper": 0.14740528258729024}, {"date": "2021-04-13", "name": "Utah", "id": "USA_US-UT", "total_count": 1, "lineage_count": 0, "cum_total_count": 347, "cum_lineage_count": 8, "proportion": 0.023054755043227664, "proportion_ci_lower": 0.010958382726754963, "proportion_ci_upper": 0.04302789139256036}, {"date": "2021-04-10", "name": "Vermont", "id": "USA_US-VT", "total_count": 1, "lineage_count": 0, "cum_total_count": 302, "cum_lineage_count": 11, "proportion": 0.03642384105960265, "proportion_ci_lower": 0.019503369354466702, "proportion_ci_upper": 0.06214923259300509}, {"date": "2021-04-16", "name": "Virginia", "id": "USA_US-VA", "total_count": 7, "lineage_count": 0, "cum_total_count": 1576, "cum_lineage_count": 59, "proportion": 0.037436548223350255, "proportion_ci_lower": 0.02889683471827624, "proportion_ci_upper": 0.04767230451397686}, {"date": "2021-04-21", "name": "Washington", "id": "USA_US-WA", "total_count": 1, "lineage_count": 0, "cum_total_count": 4725, "cum_lineage_count": 101, "proportion": 0.021375661375661374, "proportion_ci_lower": 0.01753950136574771, "proportion_ci_upper": 0.025797729616877763}, {"date": "2021-04-17", "name": "West Virginia", "id": "USA_US-WV", "total_count": 1, "lineage_count": 0, "cum_total_count": 1565, "cum_lineage_count": 18, "proportion": 0.011501597444089457, "proportion_ci_lower": 0.007077113310078825, "proportion_ci_upper": 0.017726550425006038}, {"date": "2021-04-20", "name": "Wisconsin", "id": "USA_US-WI", "total_count": 2, "lineage_count": 0, "cum_total_count": 2226, "cum_lineage_count": 75, "proportion": 0.03369272237196765, "proportion_ci_lower": 0.026792037939182004, "proportion_ci_upper": 0.0418044545533075}, {"date": "2021-04-17", "name": "Wyoming", "id": "USA_US-WY", "total_count": 2, "lineage_count": 0, "cum_total_count": 335, "cum_lineage_count": 8, "proportion": 0.023880597014925373, "proportion_ci_lower": 0.01135313306488594, "proportion_ci_upper": 0.04455160683042991}]}